{"forward_angle": {"bins": [{"bounds": [-89.83110861795477, -71.98053025096752], "median": -89.48075926238383, "probability": 0.012903225806451613, "influences": {"previous_segment_forward_angle": {"type": "Zero"}, "previous_segment_length": {"type": "Zero"}, "distance_to_last_intersection": {"type": "Zero"}}}, {"bounds": [-71.98053025096752, -54.129951883980276], "median": -61.30538094004174, "probability": 0.0064516129032258064, "influences": {"previous_segment_forward_angle": {"type": "Zero"}, "previous_segment_length": {"type": "Zero"}, "distance_to_last_intersection": {"type": "Zero"}}}, {"bounds": [-54.129951883980276, -36.27937351699303], "median": -50.32472407557415, "probability": 0.0064516129032258064, "influences": {"previous_segment_forward_angle": {"type": "Zero"}, "previous_segment_length": {"type": "Zero"}, "distance_to_last_intersection": {"type": "Zero"}}}, {"bounds": [-36.27937351699303, -18.428795150005783], "median": -25.169512982357205, "probability": 0.06451612903225806, "influences": {"previous_segment_forward_angle": {"type": "LogNormal", "s": 1.1383404553167789, "loc": -38.07999361999172, "scale": 21.12827282013444}, "previous_segment_length": {"type": "Zero"}, "distance_to_last_intersection": {"type": "Zero"}}}, {"bounds": [-18.428795150005783, -0.578216783018533], "median": -5.014331227397406, "probability": 0.3161290322580645, "influences": {"previous_segment_forward_angle": {"type": "Cauchy", "scale": 4.247357978068877, "loc": -0.6510005099993661}, "previous_segment_length": {"type": "LogNormal", "s": 1.113003049922833, "loc": 1.0890398551630391, "scale": 15.918903639315598}, "distance_to_last_intersection": {"type": "LogNormal", "s": 1.4692726138240617, "loc": 2.0639651251879974, "scale": 67.73400935111385}}}, {"bounds": [-0.578216783018533, 17.272361583968703], "median": 1.992027924369694, "probability": 0.5096774193548387, "influences": {"previous_segment_forward_angle": {"type": "Cauchy", "scale": 2.8281708085841557, "loc": 0.018568603755820402}, "previous_segment_length": {"type": "LogNormal", "s": 1.2801110133416924, "loc": 3.6616968800222787, "scale": 20.260330038745}, "distance_to_last_intersection": {"type": "LogNormal", "s": 1.6987317901421415, "loc": 3.949377081778138, "scale": 57.17478298066152}}}, {"bounds": [17.272361583968703, 35.12293995095595], "median": 23.77537246271254, "probability": 0.07096774193548387, "influences": {"previous_segment_forward_angle": {"type": "LogNormal", "s": 0.012724671424849676, "loc": -1426.4638177882048, "scale": 1434.9124431695009}, "previous_segment_length": {"type": "Cauchy", "scale": 2.116689431003599, "loc": 12.172149949227888}, "distance_to_last_intersection": {"type": "Zero"}}}, {"bounds": [35.12293995095595, 52.9735183179432], "median": 43.03035461134421, "probability": 0.012903225806451613, "influences": {"previous_segment_forward_angle": {"type": "Zero"}, "previous_segment_length": {"type": "LogNormal", "s": 19.51147567810386, "loc": 6.720999999999999, "scale": 2.643786846867974e-07}, "distance_to_last_intersection": {"type": "LogNormal", "s": 19.221543625204127, "loc": 46.65699999999999, "scale": 1.5827070390641995e-06}}}, {"bounds": [52.9735183179432, 70.82409668493044], "median": 0, "probability": 0.0, "influences": {"previous_segment_forward_angle": {"type": "Zero"}, "previous_segment_length": {"type": "Zero"}, "distance_to_last_intersection": {"type": "Zero"}}}, {"bounds": [70.82409668493044, 88.67467505191769], "median": 0, "probability": 0.0, "influences": {"previous_segment_forward_angle": {"type": "Zero"}, "previous_segment_length": {"type": "Zero"}, "distance_to_last_intersection": {"type": "Zero"}}}]}, "segment_length": {"bins": [{"bounds": [2.774, 35.114], "median": 12.085, "probability": 0.6272189349112426, "influences": {"previous_segment_forward_angle": {"type": "Cauchy", "scale": 6.166758296683694, "loc": 0.0905012602130744}, "previous_segment_length": {"type": "LogNormal", "s": 1.2944178931310306, "loc": 4.24065439697494, "scale": 12.025605693189432}, "distance_to_last_intersection": {"type": "LogNormal", "s": 1.7026713831452682, "loc": 2.532932525898448, "scale": 36.774400899836394}}}, {"bounds": [35.114, 67.454], "median": 45.85, "probability": 0.20118343195266272, "influences": {"previous_segment_forward_angle": {"type": "Cauchy", "scale": 2.389654562244106, "loc": 0.07257024166952636}, "previous_segment_length": {"type": "LogNormal", "s": 1.1108682329326365, "loc": -1.4033867232603157, "scale": 36.59561147744609}, "distance_to_last_intersection": {"type": "LogNormal", "s": 1.2892705921918128, "loc": 30.232295598179178, "scale": 89.67665869058418}}}, {"bounds": [67.454, 99.79399999999998], "median": 87.992, "probability": 0.0650887573964497, "influences": {"previous_segment_forward_angle": {"type": "Cauchy", "scale": 4.710757773498486, "loc": -0.9856080715033761}, "previous_segment_length": {"type": "LogNormal", "s": 11.362997333271418, "loc": 4.449999999999999, "scale": 0.356217077072575}, "distance_to_last_intersection": {"type": "Cauchy", "scale": 59.3258609710879, "loc": 124.69674373582643}}}, {"bounds": [99.79399999999998, 132.134], "median": 119.49350000000001, "probability": 0.023668639053254437, "influences": {"previous_segment_forward_angle": {"type": "Zero"}, "previous_segment_length": {"type": "Zero"}, "distance_to_last_intersection": {"type": "Zero"}}}, {"bounds": [132.134, 164.474], "median": 143.6735, "probability": 0.047337278106508875, "influences": {"previous_segment_forward_angle": {"type": "Zero"}, "previous_segment_length": {"type": "Zero"}, "distance_to_last_intersection": {"type": "Cauchy", "scale": 22.86697964854793, "loc": 162.68361284177809}}}, {"bounds": [164.474, 196.81399999999996], "median": 182.39499999999998, "probability": 0.023668639053254437, "influences": {"previous_segment_forward_angle": {"type": "Zero"}, "previous_segment_length": {"type": "Zero"}, "distance_to_last_intersection": {"type": "Cauchy", "scale": 26.8480766829259, "loc": 189.98476612930062}}}, {"bounds": [196.81399999999996, 229.15399999999997], "median": 215.202, "probability": 0.011834319526627219, "influences": {"previous_segment_forward_angle": {"type": "Zero"}, "previous_segment_length": {"type": "Zero"}, "distance_to_last_intersection": {"type": "LogNormal", "s": 18.169419246648168, "loc": 240.76899999999998, "scale": 2.210694411260146e-06}}}, {"bounds": [229.15399999999997, 261.49399999999997], "median": 0, "probability": 0.0, "influences": {"previous_segment_forward_angle": {"type": "Zero"}, "previous_segment_length": {"type": "Zero"}, "distance_to_last_intersection": {"type": "Zero"}}}, {"bounds": [261.49399999999997, 293.83399999999995], "median": 0, "probability": 0.0, "influences": {"previous_segment_forward_angle": {"type": "Zero"}, "previous_segment_length": {"type": "Zero"}, "distance_to_last_intersection": {"type": "Zero"}}}, {"bounds": [293.83399999999995, 326.174], "median": 0, "probability": 0.0, "influences": {"previous_segment_forward_angle": {"type": "Zero"}, "previous_segment_length": {"type": "Zero"}, "distance_to_last_intersection": {"type": "Zero"}}}]}, "next_node_degree": {"bins": [{"bounds": [1.0, 1.4], "median": 1.0, "probability": 0.05917159763313609, "influences": {"previous_segment_forward_angle": {"type": "Cauchy", "scale": 7.0233968471358645, "loc": 3.745962578321576}, "previous_segment_length": {"type": "Cauchy", "scale": 12.383104818566967, "loc": 23.107342369422405}, "distance_to_last_intersection": {"type": "Zero"}}}, {"bounds": [1.4, 1.8], "median": 0, "probability": 0.0, "influences": {"previous_segment_forward_angle": {"type": "Zero"}, "previous_segment_length": {"type": "Zero"}, "distance_to_last_intersection": {"type": "Zero"}}}, {"bounds": [1.8, 2.2], "median": 2.0, "probability": 0.621301775147929, "influences": {"previous_segment_forward_angle": {"type": "Cauchy", "scale": 5.429916268414476, "loc": 0.32655994050796333}, "previous_segment_length": {"type": "LogNormal", "s": 1.07076860817836, "loc": 1.077970871196818, "scale": 22.409826894231177}, "distance_to_last_intersection": {"type": "LogNormal", "s": 0.8091270283454092, "loc": -30.480721309920998, "scale": 163.62182773612764}}}, {"bounds": [2.2, 2.6], "median": 0, "probability": 0.0, "influences": {"previous_segment_forward_angle": {"type": "Zero"}, "previous_segment_length": {"type": "Zero"}, "distance_to_last_intersection": {"type": "Zero"}}}, {"bounds": [2.6, 3.0], "median": 0, "probability": 0.0, "influences": {"previous_segment_forward_angle": {"type": "Zero"}, "previous_segment_length": {"type": "Zero"}, "distance_to_last_intersection": {"type": "Zero"}}}, {"bounds": [3.0, 3.4000000000000004], "median": 3.0, "probability": 0.1952662721893491, "influences": {"previous_segment_forward_angle": {"type": "Cauchy", "scale": 1.3222007004299678, "loc": -0.5349645067121203}, "previous_segment_length": {"type": "Zero"}, "distance_to_last_intersection": {"type": "LogNormal", "s": 1.895334682499758, "loc": 4.219609633711221, "scale": 42.44029206820518}}}, {"bounds": [3.4000000000000004, 3.8000000000000003], "median": 0, "probability": 0.0, "influences": {"previous_segment_forward_angle": {"type": "Zero"}, "previous_segment_length": {"type": "Zero"}, "distance_to_last_intersection": {"type": "Zero"}}}, {"bounds": [3.8000000000000003, 4.2], "median": 4.0, "probability": 0.1242603550295858, "influences": {"previous_segment_forward_angle": {"type": "Cauchy", "scale": 3.8092003339725773, "loc": 0.06579964146033034}, "previous_segment_length": {"type": "Cauchy", "scale": 6.784436537646631, "loc": 11.0632076105325}, "distance_to_last_intersection": {"type": "Cauchy", "scale": 2.6878388025732813, "loc": 9.011426127912223}}}, {"bounds": [4.2, 4.6], "median": 0, "probability": 0.0, "influences": {"previous_segment_forward_angle": {"type": "Zero"}, "previous_segment_length": {"type": "Zero"}, "distance_to_last_intersection": {"type": "Zero"}}}, {"bounds": [4.6, 5.0], "median": 0, "probability": 0.0, "influences": {"previous_segment_forward_angle": {"type": "Zero"}, "previous_segment_length": {"type": "Zero"}, "distance_to_last_intersection": {"type": "Zero"}}}]}}